LICENSE
MANIFEST.in
README.md
setup.cfg
setup.py
wwpdb/__init__.py
wwpdb.apps.editormodule.egg-info/PKG-INFO
wwpdb.apps.editormodule.egg-info/SOURCES.txt
wwpdb.apps.editormodule.egg-info/dependency_links.txt
wwpdb.apps.editormodule.egg-info/not-zip-safe
wwpdb.apps.editormodule.egg-info/requires.txt
wwpdb.apps.editormodule.egg-info/top_level.txt
wwpdb/apps/__init__.py
wwpdb/apps/editormodule/__init__.py
wwpdb/apps/editormodule/config/AccessConfigCifFiles.py
wwpdb/apps/editormodule/config/AccessTemplateFiles.py
wwpdb/apps/editormodule/config/EditorConfig.py
wwpdb/apps/editormodule/config/__init__.py
wwpdb/apps/editormodule/config/pdbx_display_view_info.cif
wwpdb/apps/editormodule/config/pdbx_display_view_info_master.cif
wwpdb/apps/editormodule/depict/EditorDepict.py
wwpdb/apps/editormodule/depict/__init__.py
wwpdb/apps/editormodule/io/EditorDataImport.py
wwpdb/apps/editormodule/io/PdbxDataIo.py
wwpdb/apps/editormodule/io/PdbxMasterViewDictionary.py
wwpdb/apps/editormodule/io/PdbxMasterViewDictionaryExec.py
wwpdb/apps/editormodule/io/__init__.py
wwpdb/apps/editormodule/templates/common_tool_beta_testing_feedback.html
wwpdb/apps/editormodule/templates/editor_jmol_tmplt.html
wwpdb/apps/editormodule/templates/editor_launch_tmplt.html
wwpdb/apps/editormodule/templates/editor_launch_tmplt_config.html
wwpdb/apps/editormodule/templates/editor_launch_tmplt_scrollnav.html
wwpdb/apps/editormodule/templates/editor_prototyping.html
wwpdb/apps/editormodule/templates/editor_ui_config_admin.html
wwpdb/apps/editormodule/webapp/EditorWebApp.py
wwpdb/apps/editormodule/webapp/WebRequest.py
wwpdb/apps/editormodule/webapp/__init__.py