Metadata-Version: 2.4
Name: wwpdb.apps.editormodule
Version: 0.23.1
Summary: wwPDB mmCIF form editor module
Home-page: https://github.com/rcsb/py-wwpdb_apps_editormodule
Author: Ezra Peisach
Author-email: ezra.peisach@rcsb.org
License: Apache 2.0
Classifier: Development Status :: 3 - Alpha
Classifier: Intended Audience :: Developers
Classifier: Natural Language :: English
Classifier: License :: OSI Approved :: Apache Software License
Classifier: Programming Language :: Python
Classifier: Programming Language :: Python :: 2.7
Classifier: Programming Language :: Python :: 3
Classifier: Programming Language :: Python :: 3.6
Classifier: Programming Language :: Python :: 3.7
License-File: LICENSE
Requires-Dist: mmcif
Requires-Dist: mmcif.utils
Requires-Dist: wwpdb.utils.wf
Requires-Dist: wwpdb.utils.db[status]
Requires-Dist: wwpdb.utils.session
Requires-Dist: wwpdb.io
Requires-Dist: wwpdb.utils.config>=0.24
Requires-Dist: wwpdb.utils.dp~=0.45
Provides-Extra: dev
Requires-Dist: check-manifest; extra == "dev"
Provides-Extra: test
Requires-Dist: coverage; extra == "test"
Dynamic: author
Dynamic: author-email
Dynamic: classifier
Dynamic: description
Dynamic: home-page
Dynamic: license
Dynamic: license-file
Dynamic: provides-extra
Dynamic: requires-dist
Dynamic: summary
